finalsa/common/logger/__init__.py
finalsa/common/logger/default_settings.py
finalsa/common/logger/filter.py
finalsa/common/logger/formatter.py
finalsa_common_logger-0.0.1.data/data/LICENSE.md
finalsa_common_logger-0.0.1.dist-info/LICENSE.md
finalsa_common_logger-0.0.1.dist-info/METADATA
finalsa_common_logger-0.0.1.dist-info/WHEEL
finalsa_common_logger-0.0.1.dist-info/top_level.txt
finalsa_common_logger-0.0.1.dist-info/zip-safe
finalsa_common_logger-0.0.1.dist-info/RECORD
