Metadata-Version: 2.1
Name: finalsa-common-logger
Version: 0.0.1
Summary: An utils package for using the logger.
Home-page: https://github.com/finalsa/common-logger
Author: Luis Jimenez
Author-email: luis@finalsa.com
License: MIT
Keywords: logger
Classifier: Intended Audience :: Developers
Classifier: License :: OSI Approved :: BSD License
Classifier: Operating System :: OS Independent
Classifier: Topic :: Internet :: WWW/HTTP
Classifier: Programming Language :: Python :: 3
Classifier: Programming Language :: Python :: 3.7
Classifier: Programming Language :: Python :: 3.8
Classifier: Programming Language :: Python :: 3.9
Classifier: Programming Language :: Python :: 3.10
Requires-Python: >=3.10
License-File: LICENSE.md
Requires-Dist: finalsa-traceability >=0.0.1
Requires-Dist: python-json-logger >=2.0.7
